pyvinyl/__init__.py
pyvinyl/global_settings.py
pyvinyl/gui.py
pyvinyl/keyboard.py
pyvinyl/mouse.py
pyvinyl/process.py
pyvinyl/screen.py
pyvinyl/vinyl.pyd
pyvinyl-0.1.3.dist-info/DESCRIPTION.rst
pyvinyl-0.1.3.dist-info/METADATA
pyvinyl-0.1.3.dist-info/RECORD
pyvinyl-0.1.3.dist-info/WHEEL
pyvinyl-0.1.3.dist-info/metadata.json
pyvinyl-0.1.3.dist-info/top_level.txt
