Metadata-Version: 2.0
Name: pyvinyl
Version: 0.1.3
Summary: GUI automation utility
Home-page: https://github.com/vinyl-project/vinyl
Author: VinylProject
Author-email: admin@octoon.org
License: MIT Licence
Keywords: pip,automation,gui,test
Platform: any
Requires-Dist: numpy
